{
  "ComponentIndexes": {},
  "ControlUniqueGuids": {},
  "ControlUniqueIds": {
    "App": 1,
    "area_text": 17,
    "area_titulo": 25,
    "Container1": 7,
    "facultad_text": 15,
    "facultad_titulo": 23,
    "Gallery1": 10,
    "galleryTemplate1": 11,
    "Host": 3,
    "ID_text": 13,
    "ID_titulo": 19,
    "Inventario": 4,
    "Label5": 21,
    "local_text": 14,
    "local_titulo": 22,
    "main": 8,
    "pabellon_text": 18,
    "pabellon_titulo": 26,
    "piso_text": 16,
    "piso_titulo": 24,
    "Titulos": 9
  },
  "FunctionParamsInvariantScripts": {},
  "FunctionParamsInvariantScriptsOnInstances": {},
  "HeaderLastSavedDateTimeUTC": "10/17/2023 22:13:26",
  "IsLegacyComponentAllowGlobalScopeCase": false,
  "LocalConnectionIDReferences": {
    "a3a47bd4-af7f-4ed4-a803-86a9f94f8d5e": "\"/providers/microsoft.powerapps/apis/shared_sharepointonline/connections/0beac5f5280d43489566c0f5c36c333b\""
  },
  "LocalDatabaseReferencesAsEmpty": false,
  "LocalResourceFileNames": {},
  "LocalResourceRootPaths": {},
  "OrderComponentMetadata": {},
  "OrderComponentTemplate": {},
  "OrderDataSource": {
    "CustomGallerySample": 1,
    "INVENTARIO_EQUIPOS_INFORMATICOS": 0
  },
  "OrderGroupControls": {},
  "OrderPcfTemplate": {},
  "OrderTemplate": {},
  "OrderXMLTemplate": {
    "gallery": 2,
    "groupContainer": 1,
    "label": 0
  },
  "OverridablePropertiesEntry": {
    "App": {},
    "area_text": {},
    "area_titulo": {},
    "Container1": {},
    "facultad_text": {},
    "facultad_titulo": {},
    "Gallery1": {},
    "galleryTemplate1": {},
    "Host": {},
    "ID_text": {},
    "ID_titulo": {},
    "Inventario": {},
    "Label5": {},
    "local_text": {},
    "local_titulo": {},
    "main": {},
    "pabellon_text": {},
    "pabellon_titulo": {},
    "piso_text": {},
    "piso_titulo": {},
    "Titulos": {}
  },
  "PCFDynamicSchemaForIRRetrievalEntry": {},
  "PCFTemplateEntry": {},
  "PublishOrderIndices": {
    "App": 0,
    "area_text": 16,
    "area_titulo": 8,
    "Container1": 1,
    "facultad_text": 14,
    "facultad_titulo": 6,
    "Gallery1": 10,
    "galleryTemplate1": 11,
    "Host": 0,
    "ID_text": 12,
    "ID_titulo": 4,
    "Inventario": 0,
    "Label5": 0,
    "local_text": 13,
    "local_titulo": 5,
    "main": 2,
    "pabellon_text": 17,
    "pabellon_titulo": 9,
    "piso_text": 15,
    "piso_titulo": 7,
    "Titulos": 3
  },
  "ResourcesJsonIndices": {
    "Image-SampleImage": 0
  },
  "RuleScreenIdWithoutScreen": {},
  "TemplateVersions": {},
  "VolatileProperties": {
    "AnalysisLoadTime": 0.071917,
    "ControlCount": {
      "gallery": 1,
      "galleryTemplate": 1,
      "label": 10,
      "screen": 1
    },
    "DeserializationLoadTime": 1.5300704
  },
  "WasLocalDatabaseReferencesEmpty": true
}